component_extraction_api-0.0.1.dist-info/DESCRIPTION.rst
component_extraction_api-0.0.1.dist-info/METADATA
component_extraction_api-0.0.1.dist-info/RECORD
component_extraction_api-0.0.1.dist-info/WHEEL
component_extraction_api-0.0.1.dist-info/metadata.json
component_extraction_api-0.0.1.dist-info/top_level.txt
modules/__init__.py
modules/cef.py
modules/validators/AbstractValidator.py
modules/validators/ConfigValidator.py
modules/validators/IPUValidator.py
modules/validators/ImageValidator.py
modules/validators/JsonKeys.py
modules/validators/__init__.py
test/__init__.py
test/factory_test/__init__.py
test/factory_test/test_pipeline_factory.py
test/factory_test/test_validator_factory.py
test/pipeline_test/__init__.py
test/pipeline_test/myIPUHello.py
test/pipeline_test/test_pipeline_runner.py
test/validator_test/TestClass.py
test/validator_test/__init__.py
test/validator_test/test_config_validator.py
test/validator_test/test_image_validator.py
test/validator_test/test_ipu_validator.py
