Metadata-Version: 2.0
Name: component-extraction-api
Version: 0.0.1
Summary: Package for the Run API endpoint
Home-page: https://lapetus.bjss.com/BJSS/Academy/Leeds/2018-2019/component-extraction-framework/cef
Author: Bjss academy
Author-email: academyadamin@bjss.com
License: UNKNOWN
Platform: UNKNOWN
Classifier: Programming Language :: Python :: 3
Classifier: License :: OSI Approved :: MIT License
Classifier: Operating System :: OS Independent
